cozeloop/__init__.py
cozeloop/_client.py
cozeloop/_noop.py
cozeloop/client.py
cozeloop/decorator/__init__.py
cozeloop/decorator/decorator.py
cozeloop/decorator/utils.py
cozeloop/entities/__init__.py
cozeloop/entities/prompt.py
cozeloop/entities/stream.py
cozeloop/integration/__init__.py
cozeloop/integration/langchain/__init__.py
cozeloop/integration/langchain/trace_callback.py
cozeloop/integration/langchain/trace_model/__init__.py
cozeloop/integration/langchain/trace_model/llm_model.py
cozeloop/integration/langchain/trace_model/prompt_template.py
cozeloop/integration/langchain/trace_model/runtime.py
cozeloop/integration/langchain/util.py
cozeloop/integration/wrapper/__init__.py
cozeloop/integration/wrapper/_openai.py
cozeloop/internal/__init__.py
cozeloop/internal/consts/__init__.py
cozeloop/internal/consts/error.py
cozeloop/internal/httpclient/__init__.py
cozeloop/internal/httpclient/auth.py
cozeloop/internal/httpclient/auth_client.py
cozeloop/internal/httpclient/base_model.py
cozeloop/internal/httpclient/client.py
cozeloop/internal/httpclient/http_client.py
cozeloop/internal/httpclient/user_agent.py
cozeloop/internal/idgen/__init__.py
cozeloop/internal/idgen/idgen.py
cozeloop/internal/prompt/__init__.py
cozeloop/internal/prompt/cache.py
cozeloop/internal/prompt/converter.py
cozeloop/internal/prompt/execute_stream_reader.py
cozeloop/internal/prompt/openapi.py
cozeloop/internal/prompt/prompt.py
cozeloop/internal/stream/__init__.py
cozeloop/internal/stream/base_stream_reader.py
cozeloop/internal/stream/sse.py
cozeloop/internal/trace/__init__.py
cozeloop/internal/trace/exporter.py
cozeloop/internal/trace/model/__init__.py
cozeloop/internal/trace/model/model.py
cozeloop/internal/trace/noop_span.py
cozeloop/internal/trace/queue_manager.py
cozeloop/internal/trace/span.py
cozeloop/internal/trace/span_processor.py
cozeloop/internal/trace/trace.py
cozeloop/internal/utils/__init__.py
cozeloop/internal/utils/convert.py
cozeloop/internal/utils/get.py
cozeloop-0.1.23.dist-info/METADATA
cozeloop-0.1.23.dist-info/WHEEL
cozeloop-0.1.23.dist-info/licenses/LICENSE
cozeloop-0.1.23.dist-info/RECORD
