Metadata-Version: 2.4
Name: cozeloop
Version: 0.1.23
Summary: coze loop sdk
License: MIT
License-File: LICENSE
Author: JiangQi715
Author-email: jiangqi.rrt@bytedance.com
Requires-Python: >=3.8,<4.0
Classifier: License :: OSI Approved :: MIT License
Classifier: Programming Language :: Python :: 3
Classifier: Programming Language :: Python :: 3.8
Classifier: Programming Language :: Python :: 3.9
Classifier: Programming Language :: Python :: 3.10
Classifier: Programming Language :: Python :: 3.11
Classifier: Programming Language :: Python :: 3.12
Classifier: Programming Language :: Python :: 3.13
Classifier: Programming Language :: Python :: 3.14
Requires-Dist: apscheduler (>=3.11.0,<4.0.0)
Requires-Dist: authlib (>=1.2.0,<2.0.0)
Requires-Dist: cachetools (>=5.5.2,<7.0.0)
Requires-Dist: httpx (>=0.23.0,<1.0.0)
Requires-Dist: jinja2 (>=3.1.6,<4.0.0)
Requires-Dist: pydantic (>=1.10.12,<3.0.0)
